b2-4.5.0.dist-info/METADATA
b2-4.5.0.dist-info/WHEEL
b2-4.5.0.dist-info/entry_points.txt
b2-4.5.0.dist-info/licenses/LICENSE
b2/LICENSE
b2/__init__.py
b2/_internal/__init__.py
b2/_internal/_cli/__init__.py
b2/_internal/_cli/arg_parser_types.py
b2/_internal/_cli/argcompleters.py
b2/_internal/_cli/autocomplete_cache.py
b2/_internal/_cli/autocomplete_install.py
b2/_internal/_cli/b2api.py
b2/_internal/_cli/b2args.py
b2/_internal/_cli/const.py
b2/_internal/_cli/obj_dumps.py
b2/_internal/_cli/obj_loads.py
b2/_internal/_cli/shell.py
b2/_internal/_utils/__init__.py
b2/_internal/_utils/uri.py
b2/_internal/arg_parser.py
b2/_internal/b2v3/__init__.py
b2/_internal/b2v3/__main__.py
b2/_internal/b2v3/registry.py
b2/_internal/b2v3/rm.py
b2/_internal/b2v3/sync.py
b2/_internal/b2v4/__init__.py
b2/_internal/b2v4/__main__.py
b2/_internal/b2v4/registry.py
b2/_internal/console_tool.py
b2/_internal/json_encoder.py
b2/_internal/version.py
b2/_internal/version_listing.py
b2/licenses_output.txt
b2-4.5.0.dist-info/RECORD
